stackoverflow/__init__.py
stackoverflow2/__init__.py
stackoverflow-0.1.2.dist-info/METADATA
stackoverflow-0.1.2.dist-info/WHEEL
stackoverflow-0.1.2.dist-info/top_level.txt
stackoverflow-0.1.2.dist-info/RECORD
