Metadata-Version: 2.1
Name: stackoverflow
Version: 0.1.2
Summary: Easily use code directly from Stack Overflow
Home-page: https://github.com/drathier/stack-overflow-import
Author: https://github.com/drathier
Author-email: fille.haglund@hotmail.com
License: WTFPL
Keywords: stackoverflow development boilerplate
Platform: UNKNOWN
Classifier: Development Status :: 3 - Alpha
Classifier: Intended Audience :: Developers
Classifier: Topic :: Software Development :: Build Tools
Classifier: Programming Language :: Python :: 3
Classifier: Programming Language :: Python :: 3.3
Classifier: Programming Language :: Python :: 3.4
Classifier: Programming Language :: Python :: 3.5
Classifier: Programming Language :: Python :: 3.6
Classifier: Programming Language :: Python :: 3.6
Classifier: Programming Language :: Python :: 3.7
Classifier: Programming Language :: Python :: 3.8
Classifier: Programming Language :: Python :: 3.9
Requires-Dist: requests
Requires-Dist: beautifulsoup4
